README.md
setup.cfg
setup.py
hjnwtx/H8mess.py
hjnwtx/__init__.py
hjnwtx/cinradHJN.py
hjnwtx/colormap.py
hjnwtx/examMeso.py
hjnwtx/hjnDAAS.py
hjnwtx/hjnFTP.py
hjnwtx/hjnGIS.py
hjnwtx/hjnGPU.py
hjnwtx/hjnIDW.py
hjnwtx/hjnKDTree.py
hjnwtx/hjnLAPSTransform.py
hjnwtx/hjnLock.py
hjnwtx/hjnLog.py
hjnwtx/hjnMiscellaneous.py
hjnwtx/hjnProj.py
hjnwtx/inotify.py
hjnwtx/matplotlibMess.py
hjnwtx/mkNCHJN.py
hjnwtx/newTypeRadar.py
hjnwtx/test.py
hjnwtx/tlogP.py
hjnwtx.egg-info/PKG-INFO
hjnwtx.egg-info/SOURCES.txt
hjnwtx.egg-info/dependency_links.txt
hjnwtx.egg-info/not-zip-safe
hjnwtx.egg-info/top_level.txt