Metadata-Version: 2.1
Name: hjnwtx
Version: 0.1.18
Summary: hjn in WTX
Home-page:  
Author: hjn
Author-email: hujunnan2@126.com
License: MIT
